imageworker/__init__.py
imageworker/image.py
imageworker-0.1.12.dist-info/WHEEL
imageworker-0.1.12.dist-info/METADATA
imageworker-0.1.12.dist-info/RECORD
