Metadata-Version: 2.1
Name: imageworker
Version: 0.1.12
Summary: Lightweight image library
Author: kula
Author-email: kula@live.com
Requires-Python: >=3.6,<4.0
Classifier: Programming Language :: Python :: 3
Classifier: Programming Language :: Python :: 3.6
Classifier: Programming Language :: Python :: 3.7
Classifier: Programming Language :: Python :: 3.8
Requires-Dist: Pillow (>=8.1.2,<9.0.0)
Requires-Dist: httpx (>=0.17.1,<0.18.0)
Requires-Dist: keras_preprocessing (>=1.1.2,<2.0.0)
Requires-Dist: numpy (>=1.15.4,<2.0.0)
Requires-Dist: opencv-python (>=4.5.1,<5.0.0)
Requires-Dist: qiniu (>=7.3.1,<8.0.0)
Requires-Dist: requests (>=2.25.1,<3.0.0)
